pytest_commander/__init__.py
pytest_commander/__main__.py
pytest_commander/api.py
pytest_commander/environment.py
pytest_commander/eventlet_utils.py
pytest_commander/nodeid.py
pytest_commander/plugin.py
pytest_commander/result_tree.py
pytest_commander/runner.py
pytest_commander/watcher.py
pytest_commander/web_client/build/asset-manifest.json
pytest_commander/web_client/build/favicon.png
pytest_commander/web_client/build/index.html
pytest_commander/web_client/build/manifest.json
pytest_commander/web_client/build/robots.txt
pytest_commander/web_client/build/static/css/2.c0e8d3f0.chunk.css
pytest_commander/web_client/build/static/css/2.c0e8d3f0.chunk.css.map
pytest_commander/web_client/build/static/js/2.bb00bcbf.chunk.js
pytest_commander/web_client/build/static/js/2.bb00bcbf.chunk.js.LICENSE.txt
pytest_commander/web_client/build/static/js/2.bb00bcbf.chunk.js.map
pytest_commander/web_client/build/static/js/main.1ebdfd0c.chunk.js
pytest_commander/web_client/build/static/js/main.1ebdfd0c.chunk.js.map
pytest_commander/web_client/build/static/js/runtime-main.981618e4.js
pytest_commander/web_client/build/static/js/runtime-main.981618e4.js.map
pytest_commander-2.7.0.dist-info/LICENSE
pytest_commander-2.7.0.dist-info/METADATA
pytest_commander-2.7.0.dist-info/WHEEL
pytest_commander-2.7.0.dist-info/entry_points.txt
pytest_commander-2.7.0.dist-info/top_level.txt
pytest_commander-2.7.0.dist-info/RECORD
