Metadata-Version: 2.1
Name: pytest-commander
Version: 2.7.0
Summary: An interactive GUI test runner for PyTest
Home-page: https://github.com/ryanc414/pytest_commander
Author: Ryan Collingham
Author-email: ryanc118@gmail.com
License: UNKNOWN
Platform: UNKNOWN
Classifier: Programming Language :: Python :: 3
Classifier: License :: OSI Approved :: MIT License
Classifier: Operating System :: OS Independent
Requires-Python: >=3.6
Requires-Dist: pytest (<7.0.0,>=6.2.4)
Requires-Dist: marshmallow (<4.0.0,>=3.11.1)
Requires-Dist: marshmallow-enum (<2.0.0,>=1.5.1)
Requires-Dist: flask (<2.0.0,>=1.1.2)
Requires-Dist: flask-socketio (<6.0.0,>=5.0.1)
Requires-Dist: eventlet (<1.0.0,>=0.31.0)
Requires-Dist: watchdog (<3.0.0,>=2.1.0)
